RecSQL-0.7.11.dist-info/DESCRIPTION.rst
RecSQL-0.7.11.dist-info/METADATA
RecSQL-0.7.11.dist-info/RECORD
RecSQL-0.7.11.dist-info/WHEEL
RecSQL-0.7.11.dist-info/metadata.json
RecSQL-0.7.11.dist-info/top_level.txt
RecSQL-0.7.11.dist-info/zip-safe
recsql/__init__.py
recsql/convert.py
recsql/csv_table.py
recsql/export.py
recsql/rest_table.py
recsql/sqlarray.py
recsql/sqlfunctions.py
recsql/sqlutil.py
