Metadata-Version: 2.0
Name: RecSQL
Version: 0.7.11
Summary: Treat SQLite tables as recarrays
Home-page: https://github.com/orbeckst/RecSQL
Author: Oliver Beckstein
Author-email: orbeckst@gmail.com
License: GPLv3
Keywords: utilities numpy SQLite SQL CSV
Platform: UNKNOWN
Classifier: Development Status :: 4 - Beta
Classifier: Environment :: Console
Classifier: Intended Audience :: Developers
Classifier: Intended Audience :: Science/Research
Classifier: License :: OSI Approved :: GNU General Public License (GPL)
Classifier: Operating System :: OS Independent
Classifier: Programming Language :: Python
Classifier: Topic :: Software Development :: Libraries
Classifier: Topic :: Text Processing
Classifier: Topic :: Database
Requires-Dist: numpy (>=1.6)
